src/__init__.py
src/stuffsdk.py
stuffsdk-0.0.1.dist-info/LICENSE
stuffsdk-0.0.1.dist-info/METADATA
stuffsdk-0.0.1.dist-info/WHEEL
stuffsdk-0.0.1.dist-info/entry_points.txt
stuffsdk-0.0.1.dist-info/top_level.txt
stuffsdk-0.0.1.dist-info/RECORD
