Metadata-Version: 2.1
Name: stuffsdk
Version: 0.0.1
Summary: Stuffsdk Management Tool
Home-page: https://github.com/SpiralDeveloper/stuffsdk
Author: Ashish Sahu
Author-email: ashish@stuffsdk.com
License: UNKNOWN
Platform: UNKNOWN
Classifier: Programming Language :: Python :: 3
Classifier: License :: OSI Approved :: MIT License
Classifier: Operating System :: OS Independent
